pokemonmax/__int__.py
pokemonmax/random_pokemon.py
PokemonMax-1.0.1.dist-info/METADATA
PokemonMax-1.0.1.dist-info/WHEEL
PokemonMax-1.0.1.dist-info/top_level.txt
PokemonMax-1.0.1.dist-info/RECORD
